flake8_github/__init__.py
flake8_github/__version__.py
flake8_github-1.1.0.dist-info/LICENSE
flake8_github-1.1.0.dist-info/METADATA
flake8_github-1.1.0.dist-info/WHEEL
flake8_github-1.1.0.dist-info/entry_points.txt
flake8_github-1.1.0.dist-info/RECORD
