Metadata-Version: 2.1
Name: flake8-github
Version: 1.1.0
Summary: Flake8 formatter for GitHub Actions
Home-page: https://github.com/maxkrivich/flake8-github
License: MIT
Keywords: flake8,github,actions,formatter,linter,qa,quality,assurance,plugin,report,reporter,output,output formatter,output formatter
Author: Max Kryvych
Author-email: me@kryvych.cc
Requires-Python: >=3.8.1,<4.0.0
Classifier: Development Status :: 5 - Production/Stable
Classifier: Environment :: Console
Classifier: Framework :: Flake8
Classifier: Intended Audience :: Developers
Classifier: License :: OSI Approved :: MIT License
Classifier: Operating System :: POSIX
Classifier: Programming Language :: Python
Classifier: Programming Language :: Python :: 3
Classifier: Programming Language :: Python :: 3.9
Classifier: Programming Language :: Python :: 3.10
Classifier: Programming Language :: Python :: 3.11
Classifier: Programming Language :: Python :: 3.12
Classifier: Programming Language :: Python :: 3.8
Classifier: Topic :: Software Development :: Libraries :: Python Modules
Classifier: Topic :: Software Development :: Quality Assurance
Classifier: Typing :: Typed
Requires-Dist: flake8 (>=6.0.0,<7.0.0)
Project-URL: Bug Tracker, https://github.com/maxkrivich/flake8-github/issues
Project-URL: Repository, https://github.com/maxkrivich/flake8-github
